{
  "name": "ensure-symlink",
  "implementation": "/packages/react-native/src/executors/ensure-symlink/ensure-symlink.impl.ts",
  "schema": {
    "version": 2,
    "outputCapture": "direct-nodejs",
    "cli": "nx",
    "$id": "NxReactNativeEnsureSymlink",
    "$schema": "http://json-schema.org/schema",
    "title": "Ensure Symlink for React Native",
    "description": "Ensure workspace node_modules is symlink under app's node_modules folder.",
    "type": "object",
    "properties": {},
    "presets": []
  },
  "description": "Ensure workspace `node_modules` is symlink under app's `node_modules` folder.",
  "aliases": [],
  "hidden": false,
  "path": "/packages/react-native/src/executors/ensure-symlink/schema.json",
  "type": "executor"
}
